{"legislative_session": "86", "identifier": "HB 1043", "title": "Relating to sources of funding for the Texas emissions reduction plan.", "from_organization": "~{\"classification\": \"lower\"}", "classification": ["bill"], "subject": ["Environment--Air (I0325)", "State Finances--Management & Control (I0748)", "Vehicles & Traffic--General (I0865)", "VEHICLE EMISSIONS (S0128)", "ENVIRONMENTAL QUALITY, TEXAS COMMISSION ON (V0334)", "PUBLIC SAFETY, DEPARTMENT OF (V0251)"], "abstracts": [], "other_titles": [], "other_identifiers": [], "actions": [{"description": "Filed", "date": "2019-01-24", "organization_id": "~{\"classification\": \"lower\"}", "classification": ["filing"], "related_entities": [], "extras": {}}, {"description": "Read first time", "date": "2019-02-26", "organization_id": "~{\"classification\": \"lower\"}", "classification": ["introduction", "reading-1"], "related_entities": [], "extras": {}}, {"description": "Referred to Environmental Regulation", "date": "2019-02-26", "organization_id": "~{\"classification\": \"lower\"}", "classification": ["referral-committee"], "related_entities": [{"name": "Environmental Regulation", "entity_type": "organization", "organization_id": null}], "extras": {}}], "sponsorships": [{"name": "Blanco", "classification": "primary", "entity_type": "person", "primary": true, "person_id": "~{\"name\": \"Blanco\"}", "organization_id": null}], "related_bills": [{"identifier": "SB531", "legislative_session": "86R", "relation_type": "companion"}, {"identifier": "HB1345", "legislative_session": "86R", "relation_type": "companion"}], "versions": [{"note": "Introduced", "links": [{"url": "ftp://ftp.legis.state.tx.us/bills/86R/billtext/html/house_bills/HB01000_HB01099/HB01043I.htm", "media_type": "text/html", "text": ""}], "date": ""}], "documents": [], "sources": [{"url": "ftp://ftp.legis.state.tx.us/bills/86R/billhistory/house_bills/HB01000_HB01099/HB 1043.xml", "note": ""}], "extras": {}, "_id": "8400abd8-6de9-11e9-9a9c-8c705a93969c"}