{"legislative_session": "86", "identifier": "HB 2350", "title": "Relating to prohibition of abortion; creating a civil penalty offense; providing for a civil cause of action.", "from_organization": "~{\"classification\": \"lower\"}", "classification": ["bill"], "subject": ["Abortion (I0005)"], "abstracts": [], "other_titles": [], "other_identifiers": [], "actions": [{"description": "Filed", "date": "2019-03-08", "organization_id": "~{\"classification\": \"lower\"}", "classification": ["filing"], "related_entities": [], "extras": {}}, {"description": "Read first time", "date": "2019-03-11", "organization_id": "~{\"classification\": \"lower\"}", "classification": ["introduction", "reading-1"], "related_entities": [], "extras": {}}, {"description": "Referred to Judiciary & Civil Jurisprudence", "date": "2019-03-11", "organization_id": "~{\"classification\": \"lower\"}", "classification": ["referral-committee"], "related_entities": [{"name": "Judiciary & Civil Jurisprudence", "entity_type": "organization", "organization_id": null}], "extras": {}}, {"description": "Considered in public hearing", "date": "2019-04-01", "organization_id": "~{\"classification\": \"lower\"}", "classification": [], "related_entities": [], "extras": {}}, {"description": "Committee substitute considered in committee", "date": "2019-04-01", "organization_id": "~{\"classification\": \"lower\"}", "classification": [], "related_entities": [], "extras": {}}, {"description": "Testimony taken/registration(s) recorded in committee", "date": "2019-04-01", "organization_id": "~{\"classification\": \"lower\"}", "classification": [], "related_entities": [], "extras": {}}, {"description": "Left pending in committee", "date": "2019-04-01", "organization_id": "~{\"classification\": \"lower\"}", "classification": [], "related_entities": [], "extras": {}}], "sponsorships": [{"name": "Capriglione", "classification": "primary", "entity_type": "person", "primary": true, "person_id": "~{\"name\": \"Capriglione\"}", "organization_id": null}, {"name": "Toth", "classification": "primary", "entity_type": "person", "primary": true, "person_id": "~{\"name\": \"Toth\"}", "organization_id": null}, {"name": "Anderson, Charles \"Doc\"", "classification": "cosponsor", "entity_type": "person", "primary": false, "person_id": "~{\"name\": \"Anderson, Charles \\\"Doc\\\"\"}", "organization_id": null}, {"name": "Bonnen, Greg", "classification": "cosponsor", "entity_type": "person", "primary": false, "person_id": "~{\"name\": \"Bonnen, Greg\"}", "organization_id": null}, {"name": "Burns", "classification": "cosponsor", "entity_type": "person", "primary": false, "person_id": "~{\"name\": \"Burns\"}", "organization_id": null}, {"name": "Dean", "classification": "cosponsor", "entity_type": "person", "primary": false, "person_id": "~{\"name\": \"Dean\"}", "organization_id": null}, {"name": "Flynn", "classification": "cosponsor", "entity_type": "person", "primary": false, "person_id": "~{\"name\": \"Flynn\"}", "organization_id": null}, {"name": "Frank", "classification": "cosponsor", "entity_type": "person", "primary": false, "person_id": "~{\"name\": \"Frank\"}", "organization_id": null}, {"name": "Harris", "classification": "cosponsor", "entity_type": "person", "primary": false, "person_id": "~{\"name\": \"Harris\"}", "organization_id": null}, {"name": "Leman", "classification": "cosponsor", "entity_type": "person", "primary": false, "person_id": "~{\"name\": \"Leman\"}", "organization_id": null}, {"name": "Murr", "classification": "cosponsor", "entity_type": "person", "primary": false, "person_id": "~{\"name\": \"Murr\"}", "organization_id": null}, {"name": "Noble", "classification": "cosponsor", "entity_type": "person", "primary": false, "person_id": "~{\"name\": \"Noble\"}", "organization_id": null}, {"name": "Parker", "classification": "cosponsor", "entity_type": "person", "primary": false, "person_id": "~{\"name\": \"Parker\"}", "organization_id": null}, {"name": "Patterson", "classification": "cosponsor", "entity_type": "person", "primary": false, "person_id": "~{\"name\": \"Patterson\"}", "organization_id": null}, {"name": "Paul", "classification": "cosponsor", "entity_type": "person", "primary": false, "person_id": "~{\"name\": \"Paul\"}", "organization_id": null}, {"name": "Raney", "classification": "cosponsor", "entity_type": "person", "primary": false, "person_id": "~{\"name\": \"Raney\"}", "organization_id": null}, {"name": "Schaefer", "classification": "cosponsor", "entity_type": "person", "primary": false, "person_id": "~{\"name\": \"Schaefer\"}", "organization_id": null}, {"name": "Stephenson", "classification": "cosponsor", "entity_type": "person", "primary": false, "person_id": "~{\"name\": \"Stephenson\"}", "organization_id": null}, {"name": "Stucky", "classification": "cosponsor", "entity_type": "person", "primary": false, "person_id": "~{\"name\": \"Stucky\"}", "organization_id": null}], "related_bills": [], "versions": [{"note": "Introduced", "links": [{"url": "ftp://ftp.legis.state.tx.us/bills/86R/billtext/html/house_bills/HB02300_HB02399/HB02350I.htm", "media_type": "text/html", "text": ""}], "date": ""}], "documents": [{"note": "Fiscal Note (Introduced)", "links": [{"url": "ftp://ftp.legis.state.tx.us/bills/86R/fiscalnotes/html/house_bills/HB02300_HB02399/HB02350I.htm", "media_type": "text/html", "text": ""}], "date": ""}], "sources": [{"url": "ftp://ftp.legis.state.tx.us/bills/86R/billhistory/house_bills/HB02300_HB02399/HB 2350.xml", "note": ""}], "extras": {}, "_id": "16df0bf2-6def-11e9-9a9c-8c705a93969c"}