{"legislative_session": "86", "identifier": "HB 4290", "title": "Relating to requiring certain public retirement systems to implement funding soundness plans.", "from_organization": "~{\"classification\": \"lower\"}", "classification": ["bill"], "subject": ["Retirement Systems--General (I0725)", "STATE PENSION REVIEW BOARD (V0173)"], "abstracts": [], "other_titles": [], "other_identifiers": [], "actions": [{"description": "Filed", "date": "2019-03-08", "organization_id": "~{\"classification\": \"lower\"}", "classification": ["filing"], "related_entities": [], "extras": {}}, {"description": "Read first time", "date": "2019-03-25", "organization_id": "~{\"classification\": \"lower\"}", "classification": ["introduction", "reading-1"], "related_entities": [], "extras": {}}, {"description": "Referred to Pensions, Investments & Financial Services", "date": "2019-03-25", "organization_id": "~{\"classification\": \"lower\"}", "classification": ["referral-committee"], "related_entities": [{"name": "Pensions, Investments & Financial Services", "entity_type": "organization", "organization_id": null}], "extras": {}}], "sponsorships": [{"name": "Flynn", "classification": "primary", "entity_type": "person", "primary": true, "person_id": "~{\"name\": \"Flynn\"}", "organization_id": null}], "related_bills": [], "versions": [{"note": "Introduced", "links": [{"url": "ftp://ftp.legis.state.tx.us/bills/86R/billtext/html/house_bills/HB04200_HB04299/HB04290I.htm", "media_type": "text/html", "text": ""}], "date": ""}], "documents": [], "sources": [{"url": "ftp://ftp.legis.state.tx.us/bills/86R/billhistory/house_bills/HB04200_HB04299/HB 4290.xml", "note": ""}], "extras": {}, "_id": "ff6d76a2-6df8-11e9-9a9c-8c705a93969c"}