{"legislative_session": "86", "identifier": "HB 2749", "title": "Relating to grants for the development and operation of pretrial intervention programs for pregnant defendants.", "from_organization": "~{\"classification\": \"lower\"}", "classification": ["bill"], "subject": ["Criminal Procedure--Bail & Pretrial Release (I0202)", "Criminal Procedure--General (I0208)", "Women (I0925)", "PREGNANCY & CHILDBIRTH (S0294)"], "abstracts": [], "other_titles": [], "other_identifiers": [], "actions": [{"description": "Filed", "date": "2019-02-28", "organization_id": "~{\"classification\": \"lower\"}", "classification": ["filing"], "related_entities": [], "extras": {}}, {"description": "Read first time", "date": "2019-03-11", "organization_id": "~{\"classification\": \"lower\"}", "classification": ["introduction", "reading-1"], "related_entities": [], "extras": {}}, {"description": "Referred to Criminal Jurisprudence", "date": "2019-03-11", "organization_id": "~{\"classification\": \"lower\"}", "classification": ["referral-committee"], "related_entities": [{"name": "Criminal Jurisprudence", "entity_type": "organization", "organization_id": null}], "extras": {}}, {"description": "Withdrawn from schedule", "date": "2019-04-29", "organization_id": "~{\"classification\": \"lower\"}", "classification": [], "related_entities": [], "extras": {}}], "sponsorships": [{"name": "Neave", "classification": "primary", "entity_type": "person", "primary": true, "person_id": "~{\"name\": \"Neave\"}", "organization_id": null}], "related_bills": [], "versions": [{"note": "Introduced", "links": [{"url": "ftp://ftp.legis.state.tx.us/bills/86R/billtext/html/house_bills/HB02700_HB02799/HB02749I.htm", "media_type": "text/html", "text": ""}], "date": ""}], "documents": [], "sources": [{"url": "ftp://ftp.legis.state.tx.us/bills/86R/billhistory/house_bills/HB02700_HB02799/HB 2749.xml", "note": ""}], "extras": {}, "_id": "1a6e348a-6df1-11e9-9a9c-8c705a93969c"}