{"legislative_session": "86", "identifier": "SB 2398", "title": "Relating to establishment of the higher education pilot program for foster youth and former foster youth.", "from_organization": "~{\"classification\": \"upper\"}", "classification": ["bill"], "subject": ["Education--Higher--Institutions & Programs (I0223)", "Minors--General (I0537)", "FOSTER CARE (S0064)", "FAMILY & PROTECTIVE SERVICES, DEPARTMENT OF (V0461)"], "abstracts": [], "other_titles": [], "other_identifiers": [], "actions": [{"description": "Received by the Secretary of the Senate", "date": "2019-03-08", "organization_id": "~{\"classification\": \"upper\"}", "classification": ["filing"], "related_entities": [], "extras": {}}, {"description": "Filed", "date": "2019-03-08", "organization_id": "~{\"classification\": \"upper\"}", "classification": ["filing"], "related_entities": [], "extras": {}}, {"description": "Read first time", "date": "2019-03-21", "organization_id": "~{\"classification\": \"upper\"}", "classification": ["introduction", "reading-1"], "related_entities": [], "extras": {}}, {"description": "Referred to Health & Human Services", "date": "2019-03-21", "organization_id": "~{\"classification\": \"upper\"}", "classification": ["referral-committee"], "related_entities": [{"name": "Health & Human Services", "entity_type": "organization", "organization_id": null}], "extras": {}}], "sponsorships": [{"name": "Men\u00e9ndez", "classification": "primary", "entity_type": "person", "primary": true, "person_id": "~{\"name\": \"Men\\u00e9ndez\"}", "organization_id": null}], "related_bills": [], "versions": [{"note": "Introduced", "links": [{"url": "ftp://ftp.legis.state.tx.us/bills/86R/billtext/html/senate_bills/SB02300_SB02399/SB02398I.htm", "media_type": "text/html", "text": ""}], "date": ""}], "documents": [], "sources": [{"url": "ftp://ftp.legis.state.tx.us/bills/86R/billhistory/senate_bills/SB02300_SB02399/SB 2398.xml", "note": ""}], "extras": {}, "_id": "a49c79b8-6e0b-11e9-9a9c-8c705a93969c"}