{"legislative_session": "86", "identifier": "HR 284", "title": "Recognizing February 14, 2019, as Texas Republican County Chairmen's Association Legislative Day at the State Capitol.", "from_organization": "~{\"classification\": \"lower\"}", "classification": ["resolution"], "subject": ["REPUBLICAN COUNTY CHAIRMEN'S ASSOCIATION LEGISLATIVE DAY, TEXAS (H1554)", "Resolutions--Official Designations--Special Dates (I0721)"], "abstracts": [], "other_titles": [], "other_identifiers": [], "actions": [{"description": "Filed", "date": "2019-02-08", "organization_id": "~{\"classification\": \"lower\"}", "classification": ["filing"], "related_entities": [], "extras": {}}, {"description": "Rules suspended", "date": "2019-02-13", "organization_id": "~{\"classification\": \"lower\"}", "classification": [], "related_entities": [], "extras": {}}, {"description": "Adopted", "date": "2019-02-13", "organization_id": "~{\"classification\": \"lower\"}", "classification": ["passage"], "related_entities": [], "extras": {}}, {"description": "Reported enrolled", "date": "2019-02-21", "organization_id": "~{\"classification\": \"lower\"}", "classification": [], "related_entities": [], "extras": {}}], "sponsorships": [{"name": "Phelan", "classification": "primary", "entity_type": "person", "primary": true, "person_id": "~{\"name\": \"Phelan\"}", "organization_id": null}], "related_bills": [], "versions": [{"note": "Enrolled", "links": [{"url": "ftp://ftp.legis.state.tx.us/bills/86R/billtext/html/house_resolutions/HR00200_HR00299/HR00284F.htm", "media_type": "text/html", "text": ""}], "date": ""}, {"note": "Introduced", "links": [{"url": "ftp://ftp.legis.state.tx.us/bills/86R/billtext/html/house_resolutions/HR00200_HR00299/HR00284I.htm", "media_type": "text/html", "text": ""}], "date": ""}], "documents": [], "sources": [{"url": "ftp://ftp.legis.state.tx.us/bills/86R/billhistory/house_resolutions/HR00200_HR00299/HR 284.xml", "note": ""}], "extras": {}, "_id": "bdd6af70-6dfc-11e9-9a9c-8c705a93969c"}