{"name": "Local & Consent Calendars", "all_day": false, "start_date": "2019-04-29T05:00:00+00:00", "end_date": "", "status": "confirmed", "classification": "event", "description": "", "location": {"name": "1W.14 ", "note": "", "coordinates": null}, "media": [], "documents": [], "links": [], "participants": [{"name": "Local & Consent Calendars", "entity_type": "committee", "note": "host", "committee_id": "~{\"name\": \"Local & Consent Calendars\"}"}, {"name": "Rep. Geanie W. Morrison", "entity_type": "legislator", "note": "chair", "legislator_id": "~{\"name\": \"Rep. Geanie W. Morrison\"}"}], "agenda": [{"description": "HOUSE OF REPRESENTATIVES NOTICE OF FORMAL MEETING COMMITTEE: Local & Consent Calendars TIME & DATE: Upon final adjournment or during bill referral, if permission granted. Monday, April 29, 2019 PLACE: 1W.14 CHAIR: Rep. Geanie W. Morrison The committee will consider referred business. Notice of this meeting was announced from the house floor.", "classification": [], "related_entities": [], "subjects": [], "media": [], "notes": [], "order": "0", "extras": {}}], "sources": [{"url": "https://capitol.texas.gov/tlodocs/86R/schedules/html/C3802019042900001.HTM", "note": ""}], "extras": {}, "_id": "12c4d42a-6e12-11e9-9a9c-8c705a93969c"}