{"name": "Natural Resources & Economic Development", "all_day": false, "start_date": "2019-03-27T14:00:00+00:00", "end_date": "", "status": "confirmed", "classification": "event", "description": "", "location": {"name": "E1.012 (Hearing Room) ", "note": "", "coordinates": null}, "media": [], "documents": [], "links": [], "participants": [{"name": "Natural Resources & Economic Development", "entity_type": "committee", "note": "host", "committee_id": "~{\"name\": \"Natural Resources & Economic Development\"}"}, {"name": "Senator Brian Birdwell", "entity_type": "legislator", "note": "chair", "legislator_id": "~{\"name\": \"Senator Brian Birdwell\"}"}], "agenda": [{"description": "Bill up for discussion", "classification": [], "related_entities": [{"name": "SB 531", "entity_type": "bill", "note": "consideration", "bill_id": "~{\"identifier\": \"SB 531\"}"}], "subjects": [], "media": [], "notes": [], "order": "0", "extras": {}}, {"description": "Bill up for discussion", "classification": [], "related_entities": [{"name": "SB 534", "entity_type": "bill", "note": "consideration", "bill_id": "~{\"identifier\": \"SB 534\"}"}], "subjects": [], "media": [], "notes": [], "order": "1", "extras": {}}, {"description": "Bill up for discussion", "classification": [], "related_entities": [{"name": "SB 649", "entity_type": "bill", "note": "consideration", "bill_id": "~{\"identifier\": \"SB 649\"}"}], "subjects": [], "media": [], "notes": [], "order": "2", "extras": {}}, {"description": "Bill up for discussion", "classification": [], "related_entities": [{"name": "SB 753", "entity_type": "bill", "note": "consideration", "bill_id": "~{\"identifier\": \"SB 753\"}"}], "subjects": [], "media": [], "notes": [], "order": "3", "extras": {}}, {"description": "Bill up for discussion", "classification": [], "related_entities": [{"name": "SB 1021", "entity_type": "bill", "note": "consideration", "bill_id": "~{\"identifier\": \"SB 1021\"}"}], "subjects": [], "media": [], "notes": [], "order": "4", "extras": {}}, {"description": "Bill up for discussion", "classification": [], "related_entities": [{"name": "SB 1281", "entity_type": "bill", "note": "consideration", "bill_id": "~{\"identifier\": \"SB 1281\"}"}], "subjects": [], "media": [], "notes": [], "order": "5", "extras": {}}, {"description": "Bill up for discussion", "classification": [], "related_entities": [{"name": "SB 1488", "entity_type": "bill", "note": "consideration", "bill_id": "~{\"identifier\": \"SB 1488\"}"}], "subjects": [], "media": [], "notes": [], "order": "6", "extras": {}}, {"description": "Bill up for discussion", "classification": [], "related_entities": [{"name": "SB 1511", "entity_type": "bill", "note": "consideration", "bill_id": "~{\"identifier\": \"SB 1511\"}"}], "subjects": [], "media": [], "notes": [], "order": "7", "extras": {}}, {"description": "Bill up for discussion", "classification": [], "related_entities": [{"name": "SB 1656", "entity_type": "bill", "note": "consideration", "bill_id": "~{\"identifier\": \"SB 1656\"}"}], "subjects": [], "media": [], "notes": [], "order": "8", "extras": {}}, {"description": "Bill up for discussion", "classification": [], "related_entities": [{"name": "SB 1993", "entity_type": "bill", "note": "consideration", "bill_id": "~{\"identifier\": \"SB 1993\"}"}], "subjects": [], "media": [], "notes": [], "order": "9", "extras": {}}, {"description": "SENATE NOTICE OF PUBLIC HEARING COMMITTEE: Natural Resources & Economic Development TIME & DATE: 9:00 AM, Wednesday, March 27, 2019 PLACE: E1.012 (Hearing Room) CHAIR: Senator Brian Birdwell SB 531 Birdwell Relating to sources of funding for the Texas emissions reduction plan. SB 534 Birdwell Relating to the notice of a hearing to adopt a proposed rule under the Texas Clean Air Act. SB 649 Zaffirini Relating to promotion of the use of recyclable materials as feedstock for manufacturing. SB 753 Huffman Relating to wage requirements for community rehabilitation programs participating in the purchasing from people with disabilities program. SB 1021 Seliger | et al. Relating to the operations of the Texas Low-Level Radioactive Waste Disposal Compact waste disposal facility. SB 1281 Birdwell Relating to assessments for water and energy improvements in certain municipalities and counties. SB 1488 Buckingham Relating to the designation of a property as a historic landmark by a municipality. SB 1511 Nichols | et al. Relating to the operation of the Battleship \"Texas.\" SB 1656 Hancock Relating to the conversion of plastics and other recoverable materials through pyrolysis or gasification. SB 1993 Birdwell Relating to civil and criminal liability for engaging in certain conduct involving a critical infrastructure facility; creating criminal offenses. Public testimony will be limited to 3 minutes. If submitting written testimony, please provide 15 copies to the committee clerk with your name on each copy.", "classification": [], "related_entities": [], "subjects": [], "media": [], "notes": [], "order": "10", "extras": {}}], "sources": [{"url": "https://capitol.texas.gov/tlodocs/86R/schedules/html/C5802019032709001.HTM", "note": ""}], "extras": {}, "_id": "dbf49d28-6e10-11e9-9a9c-8c705a93969c"}