{"name": "James Talarico", "other_names": [], "identifiers": [], "gender": "", "birth_date": "", "death_date": "", "image": "https://house.texas.gov/photos/members/3685.jpg", "summary": "", "biography": "", "national_identity": "", "contact_details": [{"type": "address", "value": "Room E2.712\nP.O. Box 2910\nAustin, TX 78768", "note": "Capitol Address"}, {"type": "voice", "value": "(512) 463-0670", "note": "Capitol Address"}, {"type": "fax", "value": "(512) 463-1469", "note": "Capitol Address"}], "links": [{"note": "", "url": "https://house.texas.gov/members/member-page/?district=52"}], "sources": [{"url": "https://house.texas.gov/members/member-page/?district=52", "note": ""}], "extras": {}, "_id": "7d143e6c-6de3-11e9-9a9c-8c705a93969c"}