{"name": "Heritage Preservation Commission", "all_day": false, "start_date": "2018-08-30T21:00:00+00:00", "end_date": "", "status": "confirmed", "classification": "govt", "description": "", "location": {"name": "Dayton's Building", "note": "", "coordinates": null}, "media": [], "documents": [], "links": [], "participants": [{"name": "Heritage Preservation Commission", "entity_type": "organization", "note": "participant", "organization_id": "~{\"name\": \"Heritage Preservation Commission\"}"}], "agenda": [], "sources": [{"url": "https://lims.minneapolismn.gov/Calendar/GetCalenderList?", "note": ""}], "extras": {}, "_id": "22a6b36a-ac69-11e8-a1e4-8c705a93969c"}