{"identifier": "", "motion_text": "Subcommittee recommends reporting with substitute ", "motion_classification": ["passage"], "start_date": "2019-01-30", "result": "pass", "organization": "~{\"classification\": \"lower\"}", "legislative_session": "2019", "bill": "14926b5c-6e15-11e9-8704-8c705a93969c", "bill_action": null, "votes": [{"option": "yes", "voter_name": "Torian", "voter_id": "~{\"name\": \"Torian\"}", "note": ""}, {"option": "yes", "voter_name": "Ingram", "voter_id": "~{\"name\": \"Ingram\"}", "note": ""}, {"option": "yes", "voter_name": "Poindexter", "voter_id": "~{\"name\": \"Poindexter\"}", "note": ""}, {"option": "yes", "voter_name": "Knight", "voter_id": "~{\"name\": \"Knight\"}", "note": ""}, {"option": "yes", "voter_name": "Stolle", "voter_id": "~{\"name\": \"Stolle\"}", "note": ""}, {"option": "yes", "voter_name": "Austin", "voter_id": "~{\"name\": \"Austin\"}", "note": ""}, {"option": "yes", "voter_name": "Hayes", "voter_id": "~{\"name\": \"Hayes\"}", "note": ""}, {"option": "yes", "voter_name": "Tyler", "voter_id": "~{\"name\": \"Tyler\"}", "note": ""}], "counts": [{"option": "yes", "value": 8}, {"option": "no", "value": 0}, {"option": "other", "value": 0}], "sources": [{"url": "http://lis.virginia.gov/cgi-bin/legp604.exe?191+vot+H0204V0004+HB1668", "note": ""}], "extras": {}, "pupa_id": "http://lis.virginia.gov/cgi-bin/legp604.exe?191+vot+H0204V0004+HB1668", "_id": "1826db7c-6e15-11e9-8704-8c705a93969c"}