{"legislative_session": "101st", "identifier": "HB248", "title": "FIREARMS-JUDICIAL OFFICERS", "from_organization": "~{\"classification\": \"lower\"}", "classification": ["bill"], "subject": [], "abstracts": [{"note": "", "abstract": "Amends the Firearm Concealed Carry Act. Permits certain judicial officers, some with written consent required, to carry a concealed firearm to any building, parking area, or portion of a building under the control of an officer of the executive or legislative branch of government, any building designated for matters before a circuit court, appellate court, or the Supreme Court, or any building or portion of a building under the control of the Supreme Court and any building or portion of a building under the control of a unit of local government.", "date": ""}], "other_titles": [], "other_identifiers": [], "actions": [{"description": "Prefiled with Clerk by Rep. Margo McDermed", "date": "2019-01-08", "organization_id": "~{\"classification\": \"lower\"}", "classification": ["filing"], "related_entities": [], "extras": {}}, {"description": "First Reading", "date": "2019-01-09", "organization_id": "~{\"classification\": \"lower\"}", "classification": ["reading-1"], "related_entities": [], "extras": {}}, {"description": "Referred to Rules Committee", "date": "2019-01-09", "organization_id": "~{\"classification\": \"lower\"}", "classification": ["referral-committee"], "related_entities": [], "extras": {}}, {"description": "Added Co-Sponsor Rep. Darren Bailey", "date": "2019-01-25", "organization_id": "~{\"classification\": \"lower\"}", "classification": [], "related_entities": [], "extras": {}}, {"description": "Assigned to Judiciary - Criminal Committee", "date": "2019-01-29", "organization_id": "~{\"classification\": \"lower\"}", "classification": ["referral-committee"], "related_entities": [], "extras": {}}, {"description": "Added Co-Sponsor Rep. Tony McCombie", "date": "2019-01-30", "organization_id": "~{\"classification\": \"lower\"}", "classification": [], "related_entities": [], "extras": {}}, {"description": "To Firearms and Firearm Safety Subcommittee", "date": "2019-02-19", "organization_id": "~{\"classification\": \"lower\"}", "classification": [], "related_entities": [], "extras": {}}, {"description": "Rule 19(a) / Re-referred to Rules Committee", "date": "2019-03-29", "organization_id": "~{\"classification\": \"lower\"}", "classification": ["referral-committee"], "related_entities": [], "extras": {}}], "sponsorships": [{"name": "Margo McDermed", "classification": "primary", "entity_type": "person", "primary": false, "person_id": "~{\"name\": \"Margo McDermed\"}", "organization_id": null}], "related_bills": [], "versions": [{"note": "Introduced", "links": [{"url": "http://ilga.gov/legislation/fulltext.asp?DocName=10100HB0248&GA=101&SessionId=108&DocTypeId=HB&LegID=114187&DocNum=248&GAID=15&Session=&print=true", "media_type": "text/html", "text": ""}], "date": ""}], "documents": [], "sources": [{"url": "http://ilga.gov/legislation/BillStatus.asp?DocNum=248&GAID=15&DocTypeID=HB&LegId=114187&SessionID=108&GA=101", "note": ""}], "extras": {}, "_id": "e1bd3014-6de1-11e9-9a9b-8c705a93969c"}