{"legislative_session": "2019_20", "identifier": "SB 59", "title": "Wiretapping, Eavesdropping; it shall be legal to intercept a wire, oral, or electronic communication if all parties consent to such interception; provide", "from_organization": "~{\"classification\": \"upper\"}", "classification": ["bill"], "subject": [], "abstracts": [{"note": "description", "abstract": "A BILL to be entitled an Act to amend Part 1 of Article 3 of Chapter 11 of Title 16 of the Official Code of Georgia Annotated, relating to wiretapping, eavesdropping, surveillance, and related offenses, so as to provide that it shall be legal to intercept a wire, oral, or electronic communication if all parties to the communication consent to such interception; to provide for exceptions; to provide for related matters; to repeal conflicting laws; and for other purposes. ", "date": ""}], "other_titles": [], "other_identifiers": [], "actions": [{"description": "Senate Hopper", "date": "2019-02-05", "organization_id": "~{\"classification\": \"upper\"}", "classification": [], "related_entities": [], "extras": {}}, {"description": "Senate Read and Referred", "date": "2019-02-06", "organization_id": "~{\"classification\": \"upper\"}", "classification": ["referral-committee"], "related_entities": [{"name": "Judiciary", "entity_type": "organization", "organization_id": null}], "extras": {}}], "sponsorships": [{"name": "Jeff Mullis", "classification": "primary", "entity_type": "person", "primary": true, "person_id": "~{\"name\": \"Jeff Mullis\"}", "organization_id": null}, {"name": "John Wilkinson", "classification": "primary", "entity_type": "person", "primary": true, "person_id": "~{\"name\": \"John Wilkinson\"}", "organization_id": null}, {"name": "Butch Miller", "classification": "primary", "entity_type": "person", "primary": true, "person_id": "~{\"name\": \"Butch Miller\"}", "organization_id": null}, {"name": "Ellis Black", "classification": "primary", "entity_type": "person", "primary": true, "person_id": "~{\"name\": \"Ellis Black\"}", "organization_id": null}, {"name": "Lawrence Walker III", "classification": "primary", "entity_type": "person", "primary": true, "person_id": "~{\"name\": \"Lawrence Walker III\"}", "organization_id": null}, {"name": "Steve Gooch", "classification": "primary", "entity_type": "person", "primary": true, "person_id": "~{\"name\": \"Steve Gooch\"}", "organization_id": null}, {"name": "Mike Dugan", "classification": "primary", "entity_type": "person", "primary": true, "person_id": "~{\"name\": \"Mike Dugan\"}", "organization_id": null}, {"name": "John Albers", "classification": "primary", "entity_type": "person", "primary": true, "person_id": "~{\"name\": \"John Albers\"}", "organization_id": null}], "related_bills": [], "versions": [{"note": "As Introduced LC 28 8970", "links": [{"url": "http://www.legis.ga.gov/Legislation/20192020/180410.pdf", "media_type": "application/pdf", "text": ""}], "date": "", "extras": {"_internal_document_id": 180410, "_version_id": 2}}], "documents": [], "sources": [{"url": "http://webservices.legis.ga.gov/GGAServices/Members/Service.svc?wsdl", "note": ""}, {"url": "http://webservices.legis.ga.gov/GGAServices/Legislation/Service.svc?wsdl", "note": ""}, {"url": "http://www.legis.ga.gov/Legislation/en-US/display/2019_20/54583", "note": ""}], "extras": {"guid": 54583}, "_id": "7716a5d0-6dda-11e9-bafa-8c705a93969c"}